xianxia_quotes/__init__.py
xianxia_quotes/xianxia_quotes.py
xianxia_quotes-0.1.3.dist-info/licenses/LICENSE
xianxia_quotes-0.1.3.dist-info/METADATA
xianxia_quotes-0.1.3.dist-info/WHEEL
xianxia_quotes-0.1.3.dist-info/top_level.txt
xianxia_quotes-0.1.3.dist-info/RECORD
