Metadata-Version: 2.4
Name: xianxia-quotes
Version: 0.1.3
Summary: Generate xianxia-style proverbs.
Author-email: John Burns <john@johnburns.io>
License: GPL-3.0-or-later
Requires-Python: >=3.7
License-File: LICENSE
Dynamic: license-file
